clip_nbo/__init__.py
clip_nbo/nbo.py
clip_nbo-0.0.2.dist-info/METADATA
clip_nbo-0.0.2.dist-info/WHEEL
clip_nbo-0.0.2.dist-info/top_level.txt
clip_nbo-0.0.2.dist-info/RECORD
