Metadata-Version: 2.1
Name: clip-nbo
Version: 0.0.2
Summary: Next Best Offer Prediction
Home-page: UNKNOWN
Author: Marwa Allam and Omar Medhat
Author-email: omar.medhat965@gmail.com
License: UNKNOWN
Platform: UNKNOWN
